<annotation><filename>003261.jpg</filename><folder>parking_key_point1012_bq_L_32</folder><source><sourceImage>The MIT-CSAIL database of objects and scenes</sourceImage><sourceAnnotation>LabelMe Webtool</sourceAnnotation></source><object><name>01 key_point</name><deleted>0</deleted><verified>0</verified><occluded>no</occluded><attributes>0</attributes><parts><hasparts/><ispartof/></parts><date>13-Oct-2018 06:14:53</date><id>0</id><polygon><username>anonymous</username><pt><x>31</x><y>20</y></pt></polygon></object><object><name>02_key_point</name><deleted>0</deleted><verified>0</verified><occluded>no</occluded><attributes>0</attributes><parts><hasparts/><ispartof/></parts><date>13-Oct-2018 06:14:56</date><id>1</id><polygon><username>anonymous</username><pt><x>63</x><y>129</y></pt></polygon></object><object><name>02_key_point</name><deleted>0</deleted><verified>0</verified><occluded>no</occluded><attributes>0</attributes><parts><hasparts/><ispartof/></parts><date>13-Oct-2018 06:15:01</date><id>2</id><polygon><username>anonymous</username><pt><x>92</x><y>236</y></pt></polygon></object><object><name>03_key_point</name><deleted>0</deleted><verified>0</verified><occluded>no</occluded><attributes>0</attributes><parts><hasparts/><ispartof/></parts><date>13-Oct-2018 06:15:04</date><id>3</id><polygon><username>anonymous</username><pt><x>104</x><y>320</y></pt></polygon></object><object><name>03_key_point</name><deleted>0</deleted><verified>0</verified><occluded>no</occluded><attributes>0</attributes><parts><hasparts/><ispartof/></parts><date>13-Oct-2018 06:15:11</date><id>4</id><polygon><username>anonymous</username><pt><x>103</x><y>440</y></pt></polygon></object><object><name>04_key_point</name><deleted>0</deleted><verified>0</verified><occluded>no</occluded><attributes>0</attributes><parts><hasparts/><ispartof/></parts><date>13-Oct-2018 06:15:27</date><id>5</id><polygon><username>anonymous</username><pt><x>103</x><y>567</y></pt></polygon></object><imagesize><nrows>600</nrows><ncols>192</ncols></imagesize></annotation>